[
  {
    "lines": [
      "open [green]bio[/green].txt"
    ]
  },
  {
    "endDelay": 750,
    "showPrompt": false,
    "lines": [
      " "
    ]
  },
  {
    "charDelay": 7,
    "endDelay": 150,
    "showCursor": false,
    "lines": [
      "[green]-----[/green]",
      "Hey! 👋",
      "My name is [bold]Erlend Gjesteland Ekern[/bold].",
      "I like using [bold]technology[/bold] to solve problems.",
      "Current main areas of interest are [bold]cloud ☁️[/bold], [bold]DevOps 👷[/bold], [bold]AI 🤖[/bold] and [bold]full-stack web development 👨‍💻[/bold].",
      "I obtained my M.Sc. in [bold]Computer Science (specialization: Artificial Intelligence)[/bold] from the Norwegian University of Science and Technology in 2019."
    ],
    "showPrompt": false
  },
  {
    "showPrompt": false,
    "lines": [
      "",
      ""
    ]
  },
  {
    "lines": [
      "open [red]contact[/red].txt"
    ]
  },
  {
    "endDelay": 750,
    "showPrompt": false,
    "lines": [
      " "
    ]
  },
  {
    "showPrompt": false,
    "showCursor": false,
    "charDelay": 7,
    "endDelay": 150,
    "lines": [
      "[red]-----[/red]",
      "Email: [email]erlend@ekern.me[/email]",
      "LinkedIn: [url]https://linkedin.com/in/erlendekern[/url]",
      "Twitter: [url]https://twitter.com/erlendekern[/url]",
      "GitHub: [url]https://github.com/stekern[/url]",
      "Keybase: [url]https://keybase.io/ekern[/url]"
    ]
  },
  {
    "showPrompt": false,
    "minScreenWidth": 768,
    "lines": [
      "",
      ""
    ]
  },
  {
    "minScreenWidth": 768,
    "lines": [
      "./png_to_ascii.sh [green]picture[/green].png"
    ]
  },
  {
    "minScreenWidth": 768,
    "endDelay": 750,
    "showPrompt": false,
    "lines": [
      " "
    ]
  },
  {
    "minScreenWidth": 768,
    "showPrompt": false,
    "charDelay": 0,
    "endDelay": 0,
    "lines": [
      "[green]-----[/green]",
      "MMMMMMMMMMMMMMMMMMMMMMMMMMMMMMMMMMMMMMMMMMMMMMMMMMMMMMMMMMMMMMMMMMMMMMMMMMM",
      "MMMMMMMMMMMMMMMMMMMMMMMMMMMMMMMMMMMMMMMMMMMMMMMMMMMMMMMMMMMMMMMMMMMMMMMMMMM",
      "MMMMMMMMMMMMMMMMMMMMMMMMMMMMMMMMMMMMMMMMMMMMMMMMMMMMMMMMMMMMMMMMMMMMMMMMMMM",
      "MMMMMMMMMMMMMMMMMMMMMMMMMMMMMMMMMMMMMMMMMMMMMMMMMMMMMMMMMMMMMMMMMMMMMMMMMMM",
      "MMMMMMMMMMMMMMMMMMMMMMMMMMMMMNmmNmmdmdmNNNNMMMMMMMMMMMMMMMMMMMMMMMMMMMMMMMM",
      "MMMMMMMMMMMMMMMMMMMMMMMMNmmdhyo//+ssosoohdmmmNMMMMMMMMMMMMMMMMMMMMMMMMMMMMM",
      "MMMMMMMMMMMMMMMMMMMMMMMd::/+o::os/-:++:-//oohyhMMMMMMMMMMMMMMMMMMMMMMMMMMMM",
      "MMMMMMMMMMMMMMMMMMMMMMh-....----:/:.----..--:/oMMMMMMMMMMMMMMMMMMMMMMMMMMMM",
      "MMMMMMMMMMMMMMMMMMMMm+.`````..---....-://:://:/dMMMMMMMMMMMMMMMMMMMMMMMMMMM",
      "MMMMMMMMMMMMMMMMMMMm+-.``...-:/+oosyhdmmddhhddhsmMMMMMMMMMMMMMMMMMMMMMMMMMM",
      "MMMMMMMMMMMMMMMMMMMmy-.`.//+osyhmmNNMMNNNmmmmmdyyNMMMMMMMMMMMMMMMMMMMMMMMMM",
      "MMMMMMMMMMMMMMMMMMMMMy..:+syyhhdmmmmmmmmmmddmmmyoyMMMMMMMMMMMMMMMMMMMMMMMMM",
      "MMMMMMMMMMMMMMMMMMMMMh../syhhhhhddddddmmmdddddho//mMMMMMMMMMMMMMMMMMMMMMMMM",
      "MMMMMMMMMMMMMMMMMMMMMd../syhdddmmmmmmmmmmmmNmmho:.sMMMMMMMMMMMMMMMMMMMMMMMM",
      "MMMMMMMMMMMMMMMMMMMMNh..+oyhdhysoossyssoosyhhhdy+-+hNMMMMMMMMMMMMMMMMMMMMMM",
      "MMMMMMMMMMMMMMMMMMMMh+/-sso+/:----:+s+:--..-:/sdh/+oNMMMMMMMMMMMMMMMMMMMMMM",
      "MMMMMMMMMMMMMMMMMMMMm+//ys+/:::::-:yNh/::/+osyhdmy+hMMMMMMMMMMMMMMMMMMMMMMM",
      "MMMMMMMMMMMMMMMMMMMMNs/ssyhhhysssssdMmhyhhdmmmmddyhdMMMMMMMMMMMMMMMMMMMMMMM",
      "MMMMMMMMMMMMMMMMMMMMMhyooyddmNNNdyymNNdhhmNNmmmdyohNMMMMMMMMMMMMMMMMMMMMMMM",
      "MMMMMMMMMMMMMMMMMMMMMNds+syhhdddyosoyyososyhysosodNMMMMMMMMMMMMMMMMMMMMMMMM",
      "MMMMMMMMMMMMMMMMMMMMMMMMy++ooosoo+:-:--:ss/+++/+oMMMMMMMMMMMMMMMMMMMMMMMMMM",
      "MMMMMMMMMMMMMMMMMMMMMMMMN+++++/:/+-.---://-:o++/sMMMMMMMMMMMMMMMMMMMMMMMMMM",
      "MMMMMMMMMMMMMMMMMMMMMMMMMh//++:-:::::///++++++/-dMMMMMMMMMMMMMMMMMMMMMMMMMM",
      "MMMMMMMMMMMMMMMMMMMMMMMMMMy:/++++++////osyys+:-/mMMMMMMMMMMMMMMMMMMMMMMMMMM",
      "MMMMMMMMMMMMMMMMMMMMMMMMMMMd/:/ossssossyhhs+:.:sdNMMMMMMMMMMMMMMMMMMMMMMMMM",
      "MMMMMMMMMMMMMMMMMMMMMMMMMMMMd:-://++/////:---/shdmMdmNMMMMMMMMMMMMMMMMMMMMM",
      "MMMMMMMMMMMMMMMMMMMMMMMMMMMMNs/:-.........-/+syhmNMy/oyhhdmmNNNNMMMMMMMMMMM",
      "MMMMMMMMMMMMMMMMMMMMMMMMMMMNNds++//::--:/+oosyhmNMMm-::::://+oosyhhdmNNNNNM",
      "MMMMMMMMMMMMMMMMMMMMMMMMNmy/hmmhs++++++oooosydNNMNNm.-:::-.--:::///+ooosyyh",
      "MMMMMMMMMMMMMMMMMMMMNmhs/-.`-hdmmdys+++++oydNNNNNmNm---:::-..-----::::::::/",
      "MMMMMMMMMMMMMMMMNmhs+:-...```+mddmmmmh+-omNNNNNNNNmm/.-::::-....-----------",
      "MMMMMMMMMMMMMNdy+:--......```-hmmmmmh-..-/yNNNNMNNMMs...--...........---...",
      "MMMMMMMMMNmhs+:--........````-ydNNmd:-.-::-odNMMNMMMh......--..`....``.....",
      "MMMMMNmdyo/:---.......`.`````-NNNNmyys:-.-/dhhdNNNNNm....-..-...`...````...",
      "MMMMd+----...............```..dNNddNm+-..-/oNNNNMMMMN-.-...........`````...",
      "MMMM+-....................``..hNNNNNh/-`-+/:NNMMMMMMN/..............`````.."
    ]
  }
]
